openroute_mcp/__init__.py
openroute_mcp/py.typed
openroute_mcp/server.py
openroute_mcp/types.py
openroute_mcp/utils.py
openroute_mcp-0.0.4.dist-info/METADATA
openroute_mcp-0.0.4.dist-info/WHEEL
openroute_mcp-0.0.4.dist-info/entry_points.txt
openroute_mcp-0.0.4.dist-info/licenses/LICENSE
openroute_mcp-0.0.4.dist-info/RECORD
