Metadata-Version: 2.4
Name: openroute-mcp
Version: 0.0.4
Summary: MCP server to plan routes using OpenRouteService API, for activities such as hiking or mountain biking.
Project-URL: Homepage, https://github.com/vemonet/openroute-mcp
Project-URL: Documentation, https://github.com/vemonet/openroute-mcp
Project-URL: History, https://github.com/vemonet/openroute-mcp/releases
Project-URL: Tracker, https://github.com/vemonet/openroute-mcp/issues
Project-URL: Source, https://github.com/vemonet/openroute-mcp
Author-email: Vincent Emonet <vincent.emonet@gmail.com>
Maintainer-email: Vincent Emonet <vincent.emonet@gmail.com>
License: MIT License
License-File: LICENSE
Keywords: Chatbot,LLM,MCP,OpenRouteService
Classifier: License :: OSI Approved :: MIT License
Classifier: Operating System :: OS Independent
Classifier: Programming Language :: Python :: 3
Classifier: Programming Language :: Python :: 3.10
Classifier: Programming Language :: Python :: 3.11
Classifier: Programming Language :: Python :: 3.12
Classifier: Programming Language :: Python :: 3.13
Requires-Python: >=3.10
Requires-Dist: folium>=0.20.0
Requires-Dist: gpxpy>=1.6.2
Requires-Dist: httpx>=0.27.2
Requires-Dist: mcp>=1.16.0
Requires-Dist: pydantic>=2.11.10
Requires-Dist: staticmap>=0.5.7
Requires-Dist: uvicorn>=0.37.0
